opencode_analyzer/__init__.py
opencode_analyzer/analyzer.py
opencode_analyzer/cli.py
opencode_analyzer/data_parser.py
opencode_analyzer/data_parser_broken.py
opencode_analyzer/reporter.py
opencode_analyzer/utils.py
opencode_analyzer-0.1.0.dist-info/METADATA
opencode_analyzer-0.1.0.dist-info/WHEEL
opencode_analyzer-0.1.0.dist-info/entry_points.txt
opencode_analyzer-0.1.0.dist-info/top_level.txt
opencode_analyzer-0.1.0.dist-info/RECORD
