Metadata-Version: 2.4
Name: opencode-analyzer
Version: 0.1.0
Summary: A comprehensive tool to analyze opencode logs and provide insights into development activity
Requires-Python: >=3.13
Requires-Dist: click>=8.0.0
Requires-Dist: rich>=13.0.0
Requires-Dist: jsonschema>=4.0.0
Requires-Dist: python-dateutil>=2.8.0
Requires-Dist: pathlib2>=2.3.7
Requires-Dist: pytest>=9.0.2
Requires-Dist: orjson>=3.11.5
Requires-Dist: pytz>=2025.2
